[
    "evolution",
    {
        "entity": [
            "cppn",
            {
                "hiddens": 8,
                "inputs": 16,
                "outputs": 16
            }
        ],
        "fitness": [
            "replicate",
            {
                "env": [
                    "flip_bits",
                    {
                        "size": 16
                    }
                ],
                "num": 5
            }
        ],
        "generations": 500,
        "population_size": 100,
        "selector": [
            "elite_replacement",
            {
                "strength": 0.5
            }
        ]
    }
]
